printcolumn/__init__.py
printcolumn/colors.py
printcolumn/column_printer.py
printcolumn/core.py
printcolumn-0.1.1.dist-info/METADATA
printcolumn-0.1.1.dist-info/WHEEL
printcolumn-0.1.1.dist-info/entry_points.txt
printcolumn-0.1.1.dist-info/RECORD
