Metadata-Version: 2.4
Name: printcolumn
Version: 0.1.1
Summary: A Python utility for printing styled, aligned columns to the console.
Project-URL: Homepage, https://github.com/rlapine/PrintColumn
Project-URL: Documentation, https://github.com/rlapine/PrintColumn#readme
Project-URL: Repository, https://github.com/rlapine/PrintColumn
Author-email: Ryan LaPine <github.stunt845@passinbox.com>
Maintainer-email: Ryan LaPine <github.stunt845@passinbox.com>
License: MIT
Keywords: ANSI formatting,CLI display,Python CLI,Python utility,bold italic text,colorized output,column printer,console output,debug output,developer tools,logging enhancement,pretty print,print formatting,readable logs,styled text,tabular display,terminal formatting,text alignment,text wrapping,visual console
Classifier: Intended Audience :: Developers
Classifier: License :: OSI Approved :: MIT License
Classifier: Operating System :: OS Independent
Classifier: Programming Language :: Python :: 3
Classifier: Topic :: Software Development :: Libraries
Classifier: Topic :: Utilities
Requires-Python: >=3.8
Requires-Dist: printpop>=0.2.0
